{
  "pages": [
    {
      "path": "pages/index/index",
      "style": {
        "navigationBarTitleText": "悉尼租房小程序",
        "navigationBarBackgroundColor": "@navigationBarBackgroundColor",
        "navigationBarTextStyle": "@navigationBarTextStyle"
      }
    }
  ],
  "globalStyle": {
    "navigationBarTextStyle": "black",
    "navigationBarTitleText": "悉尼租房",
    "navigationBarBackgroundColor": "#ffffff",
    "backgroundColor": "#f4f7f9"
  },
  "tabBar": {
    "color": "#6b7280",
    "selectedColor": "#0057ff",
    "backgroundColor": "#ffffff",
    "borderStyle": "black",
    "list": [
      {
        "pagePath": "pages/index/index",
        "text": "首页",
        "iconPath": "static/icons/home.png",
        "selectedIconPath": "static/icons/home-selected.png"
      },
      {
        "pagePath": "pages/search/search",
        "text": "搜索",
        "iconPath": "static/icons/search.png",
        "selectedIconPath": "static/icons/search-selected.png"
      },
      {
        "pagePath": "pages/favorites/favorites",
        "text": "收藏",
        "iconPath": "static/icons/favorite.png",
        "selectedIconPath": "static/icons/favorite-selected.png"
      },
      {
        "pagePath": "pages/profile/profile",
        "text": "我的",
        "iconPath": "static/icons/profile.png",
        "selectedIconPath": "static/icons/profile-selected.png"
      }
    ]
  }
}
